mcp_server.py
run_server.py
server.py
iflow_mcp_mcp_logo_gen-0.1.0.dist-info/licenses/LICENSE
tools/__init__.py
tools/background_removal.py
tools/image_download.py
tools/image_gen.py
tools/image_scaling.py
iflow_mcp_mcp_logo_gen-0.1.0.dist-info/METADATA
iflow_mcp_mcp_logo_gen-0.1.0.dist-info/WHEEL
iflow_mcp_mcp_logo_gen-0.1.0.dist-info/entry_points.txt
iflow_mcp_mcp_logo_gen-0.1.0.dist-info/top_level.txt
iflow_mcp_mcp_logo_gen-0.1.0.dist-info/RECORD
