Metadata-Version: 2.4
Name: iflow-mcp_mcp-logo-gen
Version: 0.1.0
Summary: MCP Tool Server for Logo Generation using FAL AI
Requires-Python: >=3.13
License-File: LICENSE
Requires-Dist: fal-client>=0.5.9
Requires-Dist: fastapi>=0.115.11
Requires-Dist: mcp[cli]>=1.3.0
Requires-Dist: python-dotenv>=1.0.1
Requires-Dist: sse-starlette>=2.2.1
Requires-Dist: uvicorn>=0.34.0
Requires-Dist: watchdog>=4.0.0
Dynamic: license-file
